[
  {
    "total_page_number": 18
  },
  {
    "total_token": 7043
  },
  {
    "toc_content": "Specification of the AUTOSAR Network\nManagement Protocol\nAUTOSAR FO Release 1.5.0\nTable of Contents\n1 Introduction and overview 4\n1.1 Protocol purpose and objectives : 4\n1.2 Applicability of the protocol : 5\n1.2.1 Constraints and assumptions : 5\n1.2.2 Limitations : 5\n1.3 Dependencies : 5\n1.3.1 Dependencies to other protocol layers : 5\n1.3.2 Dependencies to other standards and norms : 5\n1.3.3 Dependencies to the Application Layer : 5\n2 Use Cases 6\n3 Protocol Requirements 7\n3.1 Requirements Traceability : 7\n4 Definition of terms and acronyms 8\n4.1 Acronyms and abbreviations : 8\n4.2 Definition of terms : 8\n5 Protocol specification 9\n5.1 NM message format : 9\n5.1.1 Source Node Identifier : 9\n5.1.2 Control Bit Vector : 9\n5.1.3 User Data : 10\n5.2 Partial Networking : 10\n5.2.1 Handling of Rx NM messages : 11\n5.2.2 Handling of Tx NM messages : 11\n5.3 Timing behavior : 12\n5.3.1 Sending NM message : 12\n5.3.2 Transition to Bus-Sleep Mode : 12\n5.4 Networks specifics : 13\n5.4.1 CAN and Ethernet : 13\n5.4.2 FlexRay : 13\n5.5 Sequences : 15\n5.5.1 Communication request : 15\n5.5.2 Communication release : 16\n6 Configuration parameters 17\n6.1 NM Message Layout : 17\n6.2 Timeout Parameters : 17\n7 Protocol usage and guidelines 18\n3 of 18\n\u2014 AUTOSAR CONFIDENTIAL \u2014Document ID 928: AUTOSAR_PRS_NetworkManagementProtocol",
    "toc_page_list": [
      2
    ],
    "page_index_given_in_toc": "yes"
  },
  {
    "message": "toc_with_page_number: [{'structure': '1', 'title': 'Introduction and overview', 'page': 4}, {'structure': '1.1', 'title': 'Protocol purpose and objectives', 'page': 4}, {'structure': '1.2', 'title': 'Applicability of the protocol', 'page': 5}, {'structure': '1.2.1', 'title': 'Constraints and assumptions', 'page': 5}, {'structure': '1.2.2', 'title': 'Limitations', 'page': 5}, {'structure': '1.3', 'title': 'Dependencies', 'page': 5}, {'structure': '1.3.1', 'title': 'Dependencies to other protocol layers', 'page': 5}, {'structure': '1.3.2', 'title': 'Dependencies to other standards and norms', 'page': 5}, {'structure': '1.3.3', 'title': 'Dependencies to the Application Layer', 'page': 5}, {'structure': '2', 'title': 'Use Cases', 'page': 6}, {'structure': '3', 'title': 'Protocol Requirements', 'page': 7}, {'structure': '3.1', 'title': 'Requirements Traceability', 'page': 7}, {'structure': '4', 'title': 'Definition of terms and acronyms', 'page': 8}, {'structure': '4.1', 'title': 'Acronyms and abbreviations', 'page': 8}, {'structure': '4.2', 'title': 'Definition of terms', 'page': 8}, {'structure': '5', 'title': 'Protocol specification', 'page': 9}, {'structure': '5.1', 'title': 'NM message format', 'page': 9}, {'structure': '5.1.1', 'title': 'Source Node Identifier', 'page': 9}, {'structure': '5.1.2', 'title': 'Control Bit Vector', 'page': 9}, {'structure': '5.1.3', 'title': 'User Data', 'page': 10}, {'structure': '5.2', 'title': 'Partial Networking', 'page': 10}, {'structure': '5.2.1', 'title': 'Handling of Rx NM messages', 'page': 11}, {'structure': '5.2.2', 'title': 'Handling of Tx NM messages', 'page': 11}, {'structure': '5.3', 'title': 'Timing behavior', 'page': 12}, {'structure': '5.3.1', 'title': 'Sending NM message', 'page': 12}, {'structure': '5.3.2', 'title': 'Transition to Bus-Sleep Mode', 'page': 12}, {'structure': '5.4', 'title': 'Networks specifics', 'page': 13}, {'structure': '5.4.1', 'title': 'CAN and Ethernet', 'page': 13}, {'structure': '5.4.2', 'title': 'FlexRay', 'page': 13}, {'structure': '5.5', 'title': 'Sequences', 'page': 15}, {'structure': '5.5.1', 'title': 'Communication request', 'page': 15}, {'structure': '5.5.2', 'title': 'Communication release', 'page': 16}, {'structure': '6', 'title': 'Configuration parameters', 'page': 17}, {'structure': '6.1', 'title': 'NM Message Layout', 'page': 17}, {'structure': '6.2', 'title': 'Timeout Parameters', 'page': 17}, {'structure': '7', 'title': 'Protocol usage and guidelines', 'page': 18}]"
  },
  {
    "message": "toc_with_physical_index: [{'structure': '1', 'title': 'Introduction and overview', 'physical_index': '<physical_index_4>'}, {'structure': '1.1', 'title': 'Protocol purpose and objectives', 'physical_index': '<physical_index_4>'}, {'structure': '1.2', 'title': 'Applicability of the protocol', 'physical_index': '<physical_index_5>'}, {'structure': '1.2.1', 'title': 'Constraints and assumptions', 'physical_index': '<physical_index_5>'}, {'structure': '1.2.2', 'title': 'Limitations', 'physical_index': '<physical_index_5>'}, {'structure': '1.3', 'title': 'Dependencies', 'physical_index': '<physical_index_5>'}, {'structure': '1.3.1', 'title': 'Dependencies to other protocol layers', 'physical_index': '<physical_index_5>'}, {'structure': '1.3.2', 'title': 'Dependencies to other standards and norms', 'physical_index': '<physical_index_5>'}, {'structure': '1.3.3', 'title': 'Dependencies to the Application Layer', 'physical_index': '<physical_index_5>'}, {'structure': '2', 'title': 'Use Cases', 'physical_index': '<physical_index_6>'}, {'structure': '3', 'title': 'Protocol Requirements', 'physical_index': '<physical_index_7>'}, {'structure': '3.1', 'title': 'Requirements Traceability', 'physical_index': '<physical_index_7>'}, {'structure': '4', 'title': 'Definition of terms and acronyms', 'physical_index': '<physical_index_8>'}, {'structure': '4.1', 'title': 'Acronyms and abbreviations', 'physical_index': '<physical_index_8>'}, {'structure': '4.2', 'title': 'Definition of terms', 'physical_index': '<physical_index_8>'}, {'structure': '5', 'title': 'Protocol specification', 'physical_index': '<physical_index_9>'}, {'structure': '5.1', 'title': 'NM message format', 'physical_index': '<physical_index_9>'}, {'structure': '5.1.1', 'title': 'Source Node Identifier', 'physical_index': '<physical_index_9>'}, {'structure': '5.1.2', 'title': 'Control Bit Vector', 'physical_index': '<physical_index_9>'}, {'structure': '5.1.3', 'title': 'User Data', 'physical_index': '<physical_index_10>'}, {'structure': '5.2', 'title': 'Partial Networking', 'physical_index': '<physical_index_10>'}, {'structure': '5.2.1', 'title': 'Handling of Rx NM messages', 'physical_index': '<physical_index_11>'}, {'structure': '5.2.2', 'title': 'Handling of Tx NM messages', 'physical_index': '<physical_index_11>'}, {'structure': '5.3', 'title': 'Timing behavior', 'physical_index': '<physical_index_12>'}, {'structure': '5.3.1', 'title': 'Sending NM message', 'physical_index': '<physical_index_12>'}, {'structure': '5.3.2', 'title': 'Transition to Bus-Sleep Mode', 'physical_index': '<physical_index_12>'}, {'structure': '5.4', 'title': 'Networks specifics', 'physical_index': '<physical_index_13>'}, {'structure': '5.4.1', 'title': 'CAN and Ethernet', 'physical_index': '<physical_index_13>'}, {'structure': '5.4.2', 'title': 'FlexRay', 'physical_index': '<physical_index_13>'}, {'structure': '5.5', 'title': 'Sequences', 'physical_index': '<physical_index_15>'}, {'structure': '5.5.1', 'title': 'Communication request', 'physical_index': '<physical_index_15>'}, {'structure': '5.5.2', 'title': 'Communication release', 'physical_index': '<physical_index_16>'}, {'structure': '6', 'title': 'Configuration parameters', 'physical_index': '<physical_index_17>'}, {'structure': '6.1', 'title': 'NM Message Layout', 'physical_index': '<physical_index_17>'}, {'structure': '6.2', 'title': 'Timeout Parameters', 'physical_index': '<physical_index_17>'}, {'structure': '7', 'title': 'Protocol usage and guidelines', 'physical_index': '<physical_index_18>'}]"
  },
  {
    "message": "toc_with_physical_index: [{'structure': '1', 'title': 'Introduction and overview', 'physical_index': 4}, {'structure': '1.1', 'title': 'Protocol purpose and objectives', 'physical_index': 4}, {'structure': '1.2', 'title': 'Applicability of the protocol', 'physical_index': 5}, {'structure': '1.2.1', 'title': 'Constraints and assumptions', 'physical_index': 5}, {'structure': '1.2.2', 'title': 'Limitations', 'physical_index': 5}, {'structure': '1.3', 'title': 'Dependencies', 'physical_index': 5}, {'structure': '1.3.1', 'title': 'Dependencies to other protocol layers', 'physical_index': 5}, {'structure': '1.3.2', 'title': 'Dependencies to other standards and norms', 'physical_index': 5}, {'structure': '1.3.3', 'title': 'Dependencies to the Application Layer', 'physical_index': 5}, {'structure': '2', 'title': 'Use Cases', 'physical_index': 6}, {'structure': '3', 'title': 'Protocol Requirements', 'physical_index': 7}, {'structure': '3.1', 'title': 'Requirements Traceability', 'physical_index': 7}, {'structure': '4', 'title': 'Definition of terms and acronyms', 'physical_index': 8}, {'structure': '4.1', 'title': 'Acronyms and abbreviations', 'physical_index': 8}, {'structure': '4.2', 'title': 'Definition of terms', 'physical_index': 8}, {'structure': '5', 'title': 'Protocol specification', 'physical_index': 9}, {'structure': '5.1', 'title': 'NM message format', 'physical_index': 9}, {'structure': '5.1.1', 'title': 'Source Node Identifier', 'physical_index': 9}, {'structure': '5.1.2', 'title': 'Control Bit Vector', 'physical_index': 9}, {'structure': '5.1.3', 'title': 'User Data', 'physical_index': 10}, {'structure': '5.2', 'title': 'Partial Networking', 'physical_index': 10}, {'structure': '5.2.1', 'title': 'Handling of Rx NM messages', 'physical_index': 11}, {'structure': '5.2.2', 'title': 'Handling of Tx NM messages', 'physical_index': 11}, {'structure': '5.3', 'title': 'Timing behavior', 'physical_index': 12}, {'structure': '5.3.1', 'title': 'Sending NM message', 'physical_index': 12}, {'structure': '5.3.2', 'title': 'Transition to Bus-Sleep Mode', 'physical_index': 12}, {'structure': '5.4', 'title': 'Networks specifics', 'physical_index': 13}, {'structure': '5.4.1', 'title': 'CAN and Ethernet', 'physical_index': 13}, {'structure': '5.4.2', 'title': 'FlexRay', 'physical_index': 13}, {'structure': '5.5', 'title': 'Sequences', 'physical_index': 15}, {'structure': '5.5.1', 'title': 'Communication request', 'physical_index': 15}, {'structure': '5.5.2', 'title': 'Communication release', 'physical_index': 16}, {'structure': '6', 'title': 'Configuration parameters', 'physical_index': 17}, {'structure': '6.1', 'title': 'NM Message Layout', 'physical_index': 17}, {'structure': '6.2', 'title': 'Timeout Parameters', 'physical_index': 17}, {'structure': '7', 'title': 'Protocol usage and guidelines', 'physical_index': 18}]"
  },
  {
    "message": "matching_pairs: [{'title': 'Introduction and overview', 'page': 4, 'physical_index': 4}, {'title': 'Protocol purpose and objectives', 'page': 4, 'physical_index': 4}, {'title': 'Applicability of the protocol', 'page': 5, 'physical_index': 5}, {'title': 'Constraints and assumptions', 'page': 5, 'physical_index': 5}, {'title': 'Limitations', 'page': 5, 'physical_index': 5}, {'title': 'Dependencies', 'page': 5, 'physical_index': 5}, {'title': 'Dependencies to other protocol layers', 'page': 5, 'physical_index': 5}, {'title': 'Dependencies to other standards and norms', 'page': 5, 'physical_index': 5}, {'title': 'Dependencies to the Application Layer', 'page': 5, 'physical_index': 5}, {'title': 'Use Cases', 'page': 6, 'physical_index': 6}, {'title': 'Protocol Requirements', 'page': 7, 'physical_index': 7}, {'title': 'Requirements Traceability', 'page': 7, 'physical_index': 7}, {'title': 'Definition of terms and acronyms', 'page': 8, 'physical_index': 8}, {'title': 'Acronyms and abbreviations', 'page': 8, 'physical_index': 8}, {'title': 'Definition of terms', 'page': 8, 'physical_index': 8}, {'title': 'Protocol specification', 'page': 9, 'physical_index': 9}, {'title': 'NM message format', 'page': 9, 'physical_index': 9}, {'title': 'Source Node Identifier', 'page': 9, 'physical_index': 9}, {'title': 'Control Bit Vector', 'page': 9, 'physical_index': 9}, {'title': 'User Data', 'page': 10, 'physical_index': 10}, {'title': 'Partial Networking', 'page': 10, 'physical_index': 10}, {'title': 'Handling of Rx NM messages', 'page': 11, 'physical_index': 11}, {'title': 'Handling of Tx NM messages', 'page': 11, 'physical_index': 11}, {'title': 'Timing behavior', 'page': 12, 'physical_index': 12}, {'title': 'Sending NM message', 'page': 12, 'physical_index': 12}, {'title': 'Transition to Bus-Sleep Mode', 'page': 12, 'physical_index': 12}, {'title': 'Networks specifics', 'page': 13, 'physical_index': 13}, {'title': 'CAN and Ethernet', 'page': 13, 'physical_index': 13}, {'title': 'FlexRay', 'page': 13, 'physical_index': 13}, {'title': 'Sequences', 'page': 15, 'physical_index': 15}, {'title': 'Communication request', 'page': 15, 'physical_index': 15}, {'title': 'Communication release', 'page': 16, 'physical_index': 16}, {'title': 'Configuration parameters', 'page': 17, 'physical_index': 17}, {'title': 'NM Message Layout', 'page': 17, 'physical_index': 17}, {'title': 'Timeout Parameters', 'page': 17, 'physical_index': 17}, {'title': 'Protocol usage and guidelines', 'page': 18, 'physical_index': 18}]"
  },
  {
    "message": "offset: 0"
  },
  {
    "message": "toc_with_page_number: [{'structure': '1', 'title': 'Introduction and overview', 'physical_index': 4}, {'structure': '1.1', 'title': 'Protocol purpose and objectives', 'physical_index': 4}, {'structure': '1.2', 'title': 'Applicability of the protocol', 'physical_index': 5}, {'structure': '1.2.1', 'title': 'Constraints and assumptions', 'physical_index': 5}, {'structure': '1.2.2', 'title': 'Limitations', 'physical_index': 5}, {'structure': '1.3', 'title': 'Dependencies', 'physical_index': 5}, {'structure': '1.3.1', 'title': 'Dependencies to other protocol layers', 'physical_index': 5}, {'structure': '1.3.2', 'title': 'Dependencies to other standards and norms', 'physical_index': 5}, {'structure': '1.3.3', 'title': 'Dependencies to the Application Layer', 'physical_index': 5}, {'structure': '2', 'title': 'Use Cases', 'physical_index': 6}, {'structure': '3', 'title': 'Protocol Requirements', 'physical_index': 7}, {'structure': '3.1', 'title': 'Requirements Traceability', 'physical_index': 7}, {'structure': '4', 'title': 'Definition of terms and acronyms', 'physical_index': 8}, {'structure': '4.1', 'title': 'Acronyms and abbreviations', 'physical_index': 8}, {'structure': '4.2', 'title': 'Definition of terms', 'physical_index': 8}, {'structure': '5', 'title': 'Protocol specification', 'physical_index': 9}, {'structure': '5.1', 'title': 'NM message format', 'physical_index': 9}, {'structure': '5.1.1', 'title': 'Source Node Identifier', 'physical_index': 9}, {'structure': '5.1.2', 'title': 'Control Bit Vector', 'physical_index': 9}, {'structure': '5.1.3', 'title': 'User Data', 'physical_index': 10}, {'structure': '5.2', 'title': 'Partial Networking', 'physical_index': 10}, {'structure': '5.2.1', 'title': 'Handling of Rx NM messages', 'physical_index': 11}, {'structure': '5.2.2', 'title': 'Handling of Tx NM messages', 'physical_index': 11}, {'structure': '5.3', 'title': 'Timing behavior', 'physical_index': 12}, {'structure': '5.3.1', 'title': 'Sending NM message', 'physical_index': 12}, {'structure': '5.3.2', 'title': 'Transition to Bus-Sleep Mode', 'physical_index': 12}, {'structure': '5.4', 'title': 'Networks specifics', 'physical_index': 13}, {'structure': '5.4.1', 'title': 'CAN and Ethernet', 'physical_index': 13}, {'structure': '5.4.2', 'title': 'FlexRay', 'physical_index': 13}, {'structure': '5.5', 'title': 'Sequences', 'physical_index': 15}, {'structure': '5.5.1', 'title': 'Communication request', 'physical_index': 15}, {'structure': '5.5.2', 'title': 'Communication release', 'physical_index': 16}, {'structure': '6', 'title': 'Configuration parameters', 'physical_index': 17}, {'structure': '6.1', 'title': 'NM Message Layout', 'physical_index': 17}, {'structure': '6.2', 'title': 'Timeout Parameters', 'physical_index': 17}, {'structure': '7', 'title': 'Protocol usage and guidelines', 'physical_index': 18}]"
  },
  {
    "message": "toc_with_page_number: [{'structure': '1', 'title': 'Introduction and overview', 'physical_index': 4}, {'structure': '1.1', 'title': 'Protocol purpose and objectives', 'physical_index': 4}, {'structure': '1.2', 'title': 'Applicability of the protocol', 'physical_index': 5}, {'structure': '1.2.1', 'title': 'Constraints and assumptions', 'physical_index': 5}, {'structure': '1.2.2', 'title': 'Limitations', 'physical_index': 5}, {'structure': '1.3', 'title': 'Dependencies', 'physical_index': 5}, {'structure': '1.3.1', 'title': 'Dependencies to other protocol layers', 'physical_index': 5}, {'structure': '1.3.2', 'title': 'Dependencies to other standards and norms', 'physical_index': 5}, {'structure': '1.3.3', 'title': 'Dependencies to the Application Layer', 'physical_index': 5}, {'structure': '2', 'title': 'Use Cases', 'physical_index': 6}, {'structure': '3', 'title': 'Protocol Requirements', 'physical_index': 7}, {'structure': '3.1', 'title': 'Requirements Traceability', 'physical_index': 7}, {'structure': '4', 'title': 'Definition of terms and acronyms', 'physical_index': 8}, {'structure': '4.1', 'title': 'Acronyms and abbreviations', 'physical_index': 8}, {'structure': '4.2', 'title': 'Definition of terms', 'physical_index': 8}, {'structure': '5', 'title': 'Protocol specification', 'physical_index': 9}, {'structure': '5.1', 'title': 'NM message format', 'physical_index': 9}, {'structure': '5.1.1', 'title': 'Source Node Identifier', 'physical_index': 9}, {'structure': '5.1.2', 'title': 'Control Bit Vector', 'physical_index': 9}, {'structure': '5.1.3', 'title': 'User Data', 'physical_index': 10}, {'structure': '5.2', 'title': 'Partial Networking', 'physical_index': 10}, {'structure': '5.2.1', 'title': 'Handling of Rx NM messages', 'physical_index': 11}, {'structure': '5.2.2', 'title': 'Handling of Tx NM messages', 'physical_index': 11}, {'structure': '5.3', 'title': 'Timing behavior', 'physical_index': 12}, {'structure': '5.3.1', 'title': 'Sending NM message', 'physical_index': 12}, {'structure': '5.3.2', 'title': 'Transition to Bus-Sleep Mode', 'physical_index': 12}, {'structure': '5.4', 'title': 'Networks specifics', 'physical_index': 13}, {'structure': '5.4.1', 'title': 'CAN and Ethernet', 'physical_index': 13}, {'structure': '5.4.2', 'title': 'FlexRay', 'physical_index': 13}, {'structure': '5.5', 'title': 'Sequences', 'physical_index': 15}, {'structure': '5.5.1', 'title': 'Communication request', 'physical_index': 15}, {'structure': '5.5.2', 'title': 'Communication release', 'physical_index': 16}, {'structure': '6', 'title': 'Configuration parameters', 'physical_index': 17}, {'structure': '6.1', 'title': 'NM Message Layout', 'physical_index': 17}, {'structure': '6.2', 'title': 'Timeout Parameters', 'physical_index': 17}, {'structure': '7', 'title': 'Protocol usage and guidelines', 'physical_index': 18}]"
  },
  {
    "mode": "process_toc_with_page_numbers",
    "accuracy": 0.75,
    "incorrect_results": [
      {
        "list_index": 20,
        "answer": "no",
        "title": "Partial Networking",
        "page_number": 10
      },
      {
        "list_index": 21,
        "answer": "no",
        "title": "Handling of Rx NM messages",
        "page_number": 11
      },
      {
        "list_index": 22,
        "answer": "no",
        "title": "Handling of Tx NM messages",
        "page_number": 11
      },
      {
        "list_index": 23,
        "answer": "no",
        "title": "Timing behavior",
        "page_number": 12
      },
      {
        "list_index": 24,
        "answer": "no",
        "title": "Sending NM message",
        "page_number": 12
      },
      {
        "list_index": 25,
        "answer": "no",
        "title": "Transition to Bus-Sleep Mode",
        "page_number": 12
      },
      {
        "list_index": 26,
        "answer": "no",
        "title": "Networks specifics",
        "page_number": 13
      },
      {
        "list_index": 27,
        "answer": "no",
        "title": "CAN and Ethernet",
        "page_number": 13
      },
      {
        "list_index": 28,
        "answer": "no",
        "title": "FlexRay",
        "page_number": 13
      }
    ]
  },
  {
    "message": "incorrect_results_and_range_logs: [{'list_index': 20, 'title': 'Partial Networking', 'prev_correct': 10, 'next_correct': 15}, {'list_index': 21, 'title': 'Handling of Rx NM messages', 'prev_correct': 10, 'next_correct': 15}, {'list_index': 22, 'title': 'Handling of Tx NM messages', 'prev_correct': 10, 'next_correct': 15}, {'list_index': 23, 'title': 'Timing behavior', 'prev_correct': 10, 'next_correct': 15}, {'list_index': 24, 'title': 'Sending NM message', 'prev_correct': 10, 'next_correct': 15}, {'list_index': 25, 'title': 'Transition to Bus-Sleep Mode', 'prev_correct': 10, 'next_correct': 15}, {'list_index': 26, 'title': 'Networks specifics', 'prev_correct': 10, 'next_correct': 15}, {'list_index': 27, 'title': 'CAN and Ethernet', 'prev_correct': 10, 'next_correct': 15}, {'list_index': 28, 'title': 'FlexRay', 'prev_correct': 10, 'next_correct': 15}]"
  },
  {
    "message": "invalid_results: []"
  },
  {
    "message": "Checking title appearance in start concurrently"
  },
  {
    "message": "Response: {'thinking': \"The section title 'Dependencies to the Application Layer' appears in the page_text, but it is not the first content. It appears after several other sections and text.\", 'start_begin': 'no'}"
  },
  {
    "message": "Response: {'thinking': \"The section title 'Dependencies to other standards and norms' appears in the page_text, but it is not the first content. It is preceded by other section titles and text.\", 'start_begin': 'no'}"
  },
  {
    "message": "Response: {'thinking': \"The section title 'Dependencies to other protocol layers' appears in the page_text, but it is not the first content. There are other sections and text before it.\", 'start_begin': 'no'}"
  },
  {
    "message": "Response: {}"
  },
  {
    "message": "Response: {}"
  },
  {
    "message": "Response: {}"
  },
  {
    "message": "Response: {}"
  },
  {
    "message": "Response: {}"
  },
  {
    "message": "Response: {}"
  },
  {
    "message": "Response: {'thinking': \"The section title 'Requirements Traceability' is found within the page_text, but it is not the first content. There are other contents such as the document title and section numbers before it.\", 'start_begin': 'no'}"
  },
  {
    "message": "Response: {}"
  },
  {
    "message": "Response: {}"
  },
  {
    "message": "Response: {}"
  },
  {
    "message": "Response: {}"
  },
  {
    "message": "Response: {'thinking': \"The section title 'Source Node Identifier' appears in the page_text, but it is not the first content. There are other contents before it, such as the specification details and the NM message format.\", 'start_begin': 'no'}"
  },
  {
    "message": "Response: {'thinking': \"The section title 'Constraints and assumptions' appears in the page_text, but it is not the first content. It is preceded by other text such as the specification title, version, and other section titles.\", 'start_begin': 'no'}"
  },
  {
    "message": "Response: {}"
  },
  {
    "message": "Response: {'thinking': \"The section title 'Protocol purpose and objectives' appears in the page_text, but it is not the first content. There are several lines of text before the section title, including the introduction and overview of the protocol.\", 'start_begin': 'no'}"
  },
  {
    "message": "Response: {'thinking': \"The section title 'Applicability of the protocol' appears in the page_text, but it is not the first content. There are other contents (such as the specification title and version information) before the section title.\", 'start_begin': 'no'}"
  },
  {
    "message": "Response: {'thinking': \"The given page_text starts with 'Specification of the AUTOSAR Network Management Protocol' and does not begin with the section title 'Preface'. Therefore, the section 'Preface' does not start at the beginning of the page_text.\", 'start_begin': 'no'}"
  },
  {
    "message": "Response: {'thinking': \"The section title 'Protocol Requirements' is found at the beginning of the given page_text, after some introductory text. However, since there is content before the section title, it does not start at the very beginning of the page_text.\", 'start_begin': 'no'}"
  },
  {
    "message": "Response: {'thinking': \"The section title 'Limitations' appears in the page_text, but it is not the first content. There are other sections and text before it, such as 'Specification of the AUTOSAR Network Management Protocol', version information, and other subsections.\", 'start_begin': 'no'}"
  },
  {
    "message": "Response: {'thinking': \"The section title 'Protocol specification' is not the first content in the given page_text. There are other contents such as 'Specification of the AUTOSAR Network Management Protocol AUTOSAR FO Release 1.5.0' before the section title.\", 'start_begin': 'no'}"
  },
  {
    "message": "Response: {'thinking': \"The section title 'Use Cases' appears in the page_text, but it is not the first content. There are other contents (like 'Specification of the AUTOSAR Network Management Protocol AUTOSAR FO Release 1.5.0') before the section title.\", 'start_begin': 'no'}"
  },
  {
    "message": "Response: {'thinking': \"The section title 'Introduction and overview' is present in the page_text, but it is not the first content. There are other contents such as 'Specification of the AUTOSAR Network Management Protocol AUTOSAR FO Release 1.5.0' before the section title.\", 'start_begin': 'no'}"
  },
  {
    "message": "Response: {'thinking': \"The section title 'Dependencies' appears in the page_text, but it is not the first content. There are other sections and text before it, such as 'Specification of the AUTOSAR Network Management Protocol', 'Applicability of the protocol', and 'Constraints and assumptions'.\", 'start_begin': 'no'}"
  },
  {
    "message": "Response: {'thinking': \"The section title 'Definition of terms and acronyms' appears in the page_text, but it is not the first content. There are other contents (such as 'Specification of the AUTOSAR Network Management Protocol AUTOSAR FO Release 1.5.0') before the section title.\", 'start_begin': 'no'}"
  },
  {
    "message": "Response: {'thinking': \"The section 'Control Bit Vector' appears in the page_text, but it is not at the very beginning. There are other contents such as the specification title, release version, and other section titles before it.\", 'start_begin': 'no'}"
  },
  {
    "message": "Response: {'thinking': \"The section title 'User Data' appears in the page_text, but it is not the first content. There are several lines of text and a table before the section title.\", 'start_begin': 'no'}"
  },
  {
    "message": "Response: {'thinking': \"The section title 'Partial Networking' is found in the page_text, but it is not at the very beginning. There are several lines of text and specifications before the section title appears.\", 'start_begin': 'no'}"
  },
  {
    "message": "Response: {'thinking': \"The section title 'Protocol usage and guidelines' appears in the page_text, but it is not the first content. There are other contents such as the document specification and release information before the section title.\", 'start_begin': 'no'}"
  },
  {
    "message": "Response: {'thinking': \"The section title 'Configuration parameters' appears as '6 Configuration parameters' at the beginning of the given page_text, indicating that it is the start of the section. There are no other contents before this section title.\", 'start_begin': 'yes'}"
  },
  {
    "message": "Response: {'thinking': \"The section title 'NM Message Layout' appears in the page_text, but it is not at the very beginning. There are other contents such as the specification title, release version, and a previous section title before it.\", 'start_begin': 'no'}"
  },
  {
    "message": "Response: {'thinking': \"The section title 'Acronyms and abbreviations' appears in the page_text, but it is not the first content. There are other contents before it, such as 'Specification of the AUTOSAR Network Management Protocol', version information, and the section '4 Definition of terms and acronyms'.\", 'start_begin': 'no'}"
  },
  {
    "message": "Response: {'thinking': \"The section 'Definition of terms' appears under the subsection '4.2' in the given page_text. However, it is not the first content in the page_text; there are other contents before it, including the section '4.1 Acronyms and abbreviations'.\", 'start_begin': 'no'}"
  },
  {
    "message": "Response: {'thinking': \"The section title 'CAN and Ethernet' appears in the page_text, but it is not at the very beginning. There are other contents such as 'Specification of the AUTOSAR Network Management Protocol', version information, and a note before the section title.\", 'start_begin': 'no'}"
  },
  {
    "message": "Response: {'thinking': \"The section title 'NM message format' is found at the beginning of the page_text, after some introductory text. However, since there is content before it, such as 'Specification of the AUTOSAR Network Management Protocol AUTOSAR FO Release 1.5.0 5 Protocol specification', the section does not start at the very beginning of the page_text.\", 'start_begin': 'no'}"
  }
]